{
  "id": "vesper",
  "name": "Vesper",
  "type": "dark",
  "author": "Adapted from Rauno Freiberg and vladzima/vesper-theme",
  "description": "Superset adaptation of the original Vesper peppermint and orange theme",
  "ui": {
    "background": "#101010",
    "foreground": "#FFFFFF",
    "card": "#161616",
    "cardForeground": "#FFFFFF",
    "popover": "#161616",
    "popoverForeground": "#FFFFFF",
    "primary": "#FFC799",
    "primaryForeground": "#000000",
    "secondary": "#161616",
    "secondaryForeground": "#FFFFFF",
    "muted": "#1C1C1C",
    "mutedForeground": "#A0A0A0",
    "accent": "#232323",
    "accentForeground": "#FFC799",
    "tertiary": "#101010",
    "tertiaryActive": "#232323",
    "destructive": "#FF8080",
    "destructiveForeground": "#101010",
    "border": "#282828",
    "input": "#1C1C1C",
    "ring": "#FFC799",
    "sidebar": "#101010",
    "sidebarForeground": "#A0A0A0",
    "sidebarPrimary": "#FFC799",
    "sidebarPrimaryForeground": "#000000",
    "sidebarAccent": "#161616",
    "sidebarAccentForeground": "#FFC799",
    "sidebarBorder": "#101010",
    "sidebarRing": "#FFC799",
    "chart1": "#FFC799",
    "chart2": "#99FFE4",
    "chart3": "#FF7300",
    "chart4": "#FF8080",
    "chart5": "#A0A0A0",
    "highlightMatch": "rgba(255, 199, 153, 0.2)",
    "highlightActive": "rgba(255, 199, 153, 0.35)"
  },
  "terminal": {
    "background": "#101010",
    "foreground": "#FFFFFF",
    "cursor": "#FFC799",
    "cursorAccent": "#101010",
    "selectionBackground": "rgba(255, 255, 255, 0.15)",
    "black": "#101010",
    "red": "#FF8080",
    "green": "#99FFE4",
    "yellow": "#FFC799",
    "blue": "#A0A0A0",
    "magenta": "#FF7300",
    "cyan": "#99FFE4",
    "white": "#FFFFFF",
    "brightBlack": "#505050",
    "brightRed": "#FF8080",
    "brightGreen": "#99FFE4",
    "brightYellow": "#FFCFA8",
    "brightBlue": "#A0A0A0",
    "brightMagenta": "#FF8080",
    "brightCyan": "#99FFE4",
    "brightWhite": "#ffffff"
  }
}
